[
  { "id": 1772, "value": "受容" },
  { "id": 1773, "value": "達成" },
  { "id": 1774, "value": "活動主義" },
  { "id": 1775, "value": "適応" },
  { "id": 1776, "value": "賞賛" },
  { "id": 1777, "value": "進歩" },
  { "id": 1778, "value": "冒険" },
  { "id": 1779, "value": "提唱" },
  { "id": 1780, "value": "年齢" },
  { "id": 1781, "value": "不可知論" },
  { "id": 1782, "value": "錬金術" },
  { "id": 1783, "value": "同盟" },
  { "id": 1784, "value": "利他主義" },
  { "id": 1785, "value": "野心" },
  { "id": 1786, "value": "分析" },
  { "id": 1787, "value": "無政府主義" },
  { "id": 1788, "value": "無政府主義" },
  { "id": 1789, "value": "古代" },
  { "id": 1790, "value": "政府" },
  { "id": 1791, "value": "アニミズム" },
  { "id": 1792, "value": "不安" },
  { "id": 1793, "value": "議論" },
  { "id": 1794, "value": "貴族主義" },
  { "id": 1795, "value": "傲慢さ" },
  { "id": 1796, "value": "芸術" },
  { "id": 1797, "value": "記事" },
  { "id": 1798, "value": "願望" },
  { "id": 1799, "value": "無神論" },
  { "id": 1800, "value": "真正性" },
  { "id": 1801, "value": "権威" },
  { "id": 1802, "value": "覚醒" },
  { "id": 1803, "value": "畏敬の念" },
  { "id": 1804, "value": "アステカ" },
  { "id": 1805, "value": "戦い" },
  { "id": 1806, "value": "美しさ" },
  { "id": 1807, "value": "信念" },
  { "id": 1808, "value": "偏見" },
  { "id": 1809, "value": "伝記" },
  { "id": 1810, "value": "青銅" },
  { "id": 1811, "value": "仏教" },
  { "id": 1812, "value": "建物" },
  { "id": 1813, "value": "資本主義" },
  { "id": 1814, "value": "大惨事" },
  { "id": 1815, "value": "確実性" },
  { "id": 1816, "value": "挑戦" },
  { "id": 1817, "value": "変化" },
  { "id": 1818, "value": "慈善" },
  { "id": 1819, "value": "中国" },
  { "id": 1820, "value": "キリスト教" },
  { "id": 1821, "value": "都市" },
  { "id": 1822, "value": "連合" },
  { "id": 1823, "value": "政策" },
  { "id": 1824, "value": "植民地化" },
  { "id": 1825, "value": "コミットメント" },
  { "id": 1826, "value": "共産主義" },
  { "id": 1827, "value": "思いやり" },
  { "id": 1828, "value": "競争" },
  { "id": 1829, "value": "複雑性" },
  { "id": 1830, "value": "概念" },
  { "id": 1831, "value": "自信" },
  { "id": 1832, "value": "対立" },
  { "id": 1833, "value": "征服" },
  { "id": 1834, "value": "良心" },
  { "id": 1835, "value": "保守主義" },
  { "id": 1836, "value": "建設" },
  { "id": 1837, "value": "現代的" },
  { "id": 1838, "value": "制御" },
  { "id": 1839, "value": "腐敗" },
  { "id": 1840, "value": "勇気" },
  { "id": 1841, "value": "創造" },
  { "id": 1842, "value": "創造性" },
  { "id": 1843, "value": "犯罪" },
  { "id": 1844, "value": "危機" },
  { "id": 1845, "value": "批判" },
  { "id": 1846, "value": "文化" },
  { "id": 1847, "value": "好奇心" },
  { "id": 1848, "value": "政治" },
  { "id": 1849, "value": "討論" },
  { "id": 1850, "value": "腐敗" },
  { "id": 1851, "value": "衰退" },
  { "id": 1852, "value": "献身" },
  { "id": 1853, "value": "敗北" },
  { "id": 1854, "value": "民主主義" },
  { "id": 1855, "value": "哲学" },
  { "id": 1856, "value": "社会" },
  { "id": 1857, "value": "農業" },
  { "id": 1858, "value": "開発" },
  { "id": 1859, "value": "献身" },
  { "id": 1860, "value": "対話" },
  { "id": 1861, "value": "日記" },
  { "id": 1862, "value": "独裁" },
  { "id": 1863, "value": "困難" },
  { "id": 1864, "value": "拡散" },
  { "id": 1865, "value": "尊厳" },
  { "id": 1866, "value": "ジレンマ" },
  { "id": 1867, "value": "災害" },
  { "id": 1868, "value": "規律" },
  { "id": 1869, "value": "発見" },
  { "id": 1870, "value": "病気" },
  { "id": 1871, "value": "論文" },
  { "id": 1872, "value": "多様性" },
  { "id": 1873, "value": "独断主義" },
  { "id": 1874, "value": "支配" },
  { "id": 1875, "value": "疑い" },
  { "id": 1876, "value": "ドラマ" },
  { "id": 1877, "value": "夢" },
  { "id": 1878, "value": "義務" },
  { "id": 1879, "value": "ディストピア" },
  { "id": 1880, "value": "初期" },
  { "id": 1881, "value": "経済" },
  { "id": 1882, "value": "教育" },
  { "id": 1883, "value": "エジプト" },
  { "id": 1884, "value": "移民" },
  { "id": 1885, "value": "共感" },
  { "id": 1886, "value": "帝国" },
  { "id": 1887, "value": "啓蒙" },
  { "id": 1888, "value": "羨望" },
  { "id": 1889, "value": "叙事詩" },
  { "id": 1890, "value": "平等" },
  { "id": 1891, "value": "エッセイ" },
  { "id": 1892, "value": "倫理" },
  { "id": 1893, "value": "証拠" },
  { "id": 1894, "value": "進化" },
  { "id": 1895, "value": "卓越性" },
  { "id": 1896, "value": "交換" },
  { "id": 1897, "value": "拡大" },
  { "id": 1898, "value": "実験" },
  { "id": 1899, "value": "専門知識" },
  { "id": 1900, "value": "搾取" },
  { "id": 1901, "value": "探査" },
  { "id": 1902, "value": "過激主義" },
  { "id": 1903, "value": "事実" },
  { "id": 1904, "value": "信仰" },
  { "id": 1905, "value": "誤謬" },
  { "id": 1906, "value": "狂信" },
  { "id": 1907, "value": "ファシズム" },
  { "id": 1908, "value": "恐怖" },
  { "id": 1909, "value": "連邦" },
  { "id": 1910, "value": "封建主義" },
  { "id": 1911, "value": "忠誠" },
  { "id": 1912, "value": "許し" },
  { "id": 1913, "value": "自由" },
  { "id": 1914, "value": "基本的" },
  { "id": 1915, "value": "未来主義" },
  { "id": 1916, "value": "寛大さ" },
  { "id": 1917, "value": "天才" },
  { "id": 1918, "value": "本物" },
  { "id": 1919, "value": "グローバル" },
  { "id": 1920, "value": "グノーシス主義" },
  { "id": 1921, "value": "目標" },
  { "id": 1922, "value": "善良さ" },
  { "id": 1923, "value": "感謝" },
  { "id": 1924, "value": "ギリシャ" },
  { "id": 1925, "value": "貪欲" },
  { "id": 1926, "value": "紙" },
  { "id": 1927, "value": "成長" },
  { "id": 1928, "value": "苦難" },
  { "id": 1929, "value": "調和" },
  { "id": 1930, "value": "インク" },
  { "id": 1931, "value": "癒し" },
  { "id": 1932, "value": "神秘主義" },
  { "id": 1933, "value": "ヒンズー教" },
  { "id": 1934, "value": "歴史" },
  { "id": 1935, "value": "礼儀正しさ" },
  { "id": 1936, "value": "誠実さ" },
  { "id": 1937, "value": "名誉" },
  { "id": 1938, "value": "希望" },
  { "id": 1939, "value": "ヒューマニズム" },
  { "id": 1940, "value": "人間性" },
  { "id": 1941, "value": "謙虚さ" },
  { "id": 1942, "value": "飢餓" },
  { "id": 1943, "value": "仮説" },
  { "id": 1944, "value": "アイデア" },
  { "id": 1945, "value": "無知" },
  { "id": 1946, "value": "病気" },
  { "id": 1947, "value": "啓蒙" },
  { "id": 1948, "value": "想像力" },
  { "id": 1949, "value": "移民" },
  { "id": 1950, "value": "帝国主義" },
  { "id": 1951, "value": "改善" },
  { "id": 1952, "value": "インカ" },
  { "id": 1953, "value": "インダス" },
  { "id": 1954, "value": "不平等" },
  { "id": 1955, "value": "傷害" },
  { "id": 1956, "value": "不正義" },
  { "id": 1957, "value": "革新" },
  { "id": 1958, "value": "調査" },
  { "id": 1959, "value": "インスピレーション" },
  { "id": 1960, "value": "誠実さ" },
  { "id": 1961, "value": "相互作用" },
  { "id": 1962, "value": "発明" },
  { "id": 1963, "value": "調査" },
  { "id": 1964, "value": "鉄" },
  { "id": 1965, "value": "イスラム教" },
  { "id": 1966, "value": "ジャイナ教" },
  { "id": 1967, "value": "産業" },
  { "id": 1968, "value": "ジャーナル" },
  { "id": 1969, "value": "旅" },
  { "id": 1970, "value": "喜び" },
  { "id": 1971, "value": "ユダヤ教" },
  { "id": 1972, "value": "正義" },
  { "id": 1973, "value": "カバラ" },
  { "id": 1974, "value": "親切" },
  { "id": 1975, "value": "王国" },
  { "id": 1976, "value": "知識" },
  { "id": 1977, "value": "言語" },
  { "id": 1978, "value": "法律" },
  { "id": 1979, "value": "リーダーシップ" },
  { "id": 1980, "value": "リーグ" },
  { "id": 1981, "value": "学習" },
  { "id": 1982, "value": "伝説" },
  { "id": 1983, "value": "手紙" },
  { "id": 1984, "value": "自由主義" },
  { "id": 1985, "value": "自由" },
  { "id": 1986, "value": "論理" },
  { "id": 1987, "value": "音楽" },
  { "id": 1988, "value": "愛" },
  { "id": 1989, "value": "忠誠心" },
  { "id": 1990, "value": "欲望" },
  { "id": 1991, "value": "習得" },
  { "id": 1992, "value": "成熟" },
  { "id": 1993, "value": "マヤ" },
  { "id": 1994, "value": "中世" },
  { "id": 1995, "value": "瞑想" },
  { "id": 1996, "value": "指導" },
  { "id": 1997, "value": "メソポタミア" },
  { "id": 1998, "value": "道路" },
  { "id": 1999, "value": "移住" },
  { "id": 2000, "value": "通貨" },
  { "id": 2001, "value": "軍事" },
  { "id": 2002, "value": "使命" },
  { "id": 2003, "value": "現代" },
  { "id": 2004, "value": "モダニズム" },
  { "id": 2005, "value": "君主制" },
  { "id": 2006, "value": "一神教" },
  { "id": 2007, "value": "道徳" },
  { "id": 2008, "value": "動機" },
  { "id": 2009, "value": "神秘主義" },
  { "id": 2010, "value": "神話" },
  { "id": 2011, "value": "ナショナリズム" },
  { "id": 2012, "value": "ナビゲーション" },
  { "id": 2013, "value": "反省" },
  { "id": 2014, "value": "新石器時代" },
  { "id": 2015, "value": "小説" },
  { "id": 2016, "value": "観察" },
  { "id": 2017, "value": "障害" },
  { "id": 2018, "value": "寡頭制" },
  { "id": 2019, "value": "大学" },
  { "id": 2020, "value": "独創性" },
  { "id": 2021, "value": "痛み" },
  { "id": 2022, "value": "パラドックス" },
  { "id": 2023, "value": "忍耐" },
  { "id": 2024, "value": "愛国心" },
  { "id": 2025, "value": "平和" },
  { "id": 2026, "value": "完璧" },
  { "id": 2027, "value": "忍耐" },
  { "id": 2028, "value": "ペルシャ" },
  { "id": 2029, "value": "慈善活動" },
  { "id": 2030, "value": "金権政治" },
  { "id": 2031, "value": "詩" },
  { "id": 2032, "value": "多神教" },
  { "id": 2033, "value": "人口" },
  { "id": 2034, "value": "ポストモダン" },
  { "id": 2035, "value": "貧困" },
  { "id": 2036, "value": "権力" },
  { "id": 2037, "value": "祈り" },
  { "id": 2038, "value": "偏見" },
  { "id": 2039, "value": "プライド" },
  { "id": 2040, "value": "原則" },
  { "id": 2041, "value": "問題" },
  { "id": 2042, "value": "生産" },
  { "id": 2043, "value": "進歩" },
  { "id": 2044, "value": "証明" },
  { "id": 2045, "value": "目的" },
  { "id": 2046, "value": "追求" },
  { "id": 2047, "value": "探求" },
  { "id": 2048, "value": "質問" },
  { "id": 2049, "value": "summeria" },
  { "id": 2050, "value": "急進主義" },
  { "id": 2051, "value": "理由" },
  { "id": 2052, "value": "反乱" },
  { "id": 2053, "value": "再生" },
  { "id": 2054, "value": "回復" },
  { "id": 2055, "value": "改革" },
  { "id": 2056, "value": "宗教" },
  { "id": 2057, "value": "ルネッサンス" },
  { "id": 2058, "value": "報告" },
  { "id": 2059, "value": "共和国" },
  { "id": 2060, "value": "研究" },
  { "id": 2061, "value": "回復力" },
  { "id": 2062, "value": "抵抗" },
  { "id": 2063, "value": "尊敬" },
  { "id": 2064, "value": "責任" },
  { "id": 2066, "value": "畏敬" },
  { "id": 2067, "value": "レビュー" },
  { "id": 2068, "value": "革命" },
  { "id": 2069, "value": "権利" },
  { "id": 2070, "value": "儀式" },
  { "id": 2071, "value": "ライバル関係" },
  { "id": 2072, "value": "ロマン主義" },
  { "id": 2073, "value": "ローマ" },
  { "id": 2074, "value": "犠牲" },
  { "id": 2075, "value": "スキャンダル" },
  { "id": 2076, "value": "学問" },
  { "id": 2077, "value": "科学" },
  { "id": 2078, "value": "検索" },
  { "id": 2079, "value": "宗派主義" },
  { "id": 2080, "value": "世俗主義" },
  { "id": 2081, "value": "無私" },
  { "id": 2082, "value": "説教" },
  { "id": 2083, "value": "奉仕" },
  { "id": 2084, "value": "車輪" },
  { "id": 2085, "value": "神道" },
  { "id": 2086, "value": "シーク教" },
  { "id": 2087, "value": "シンプルさ" },
  { "id": 2088, "value": "誠実さ" },
  { "id": 2089, "value": "スキル" },
  { "id": 2090, "value": "社会主義" },
  { "id": 2091, "value": "解決策" },
  { "id": 2092, "value": "スピーチ" },
  { "id": 2093, "value": "状態" },
  { "id": 2094, "value": "闘争" },
  { "id": 2095, "value": "勉強" },
  { "id": 2096, "value": "成功" },
  { "id": 2097, "value": "立法" },
  { "id": 2098, "value": "スーフィズム" },
  { "id": 2099, "value": "生存" },
  { "id": 2100, "value": "共感" },
  { "id": 2101, "value": "統合" },
  { "id": 2102, "value": "才能" },
  { "id": 2103, "value": "道教" },
  { "id": 2104, "value": "教育" },
  { "id": 2105, "value": "富" },
  { "id": 2106, "value": "神権政治" },
  { "id": 2107, "value": "理論" },
  { "id": 2108, "value": "論文" },
  { "id": 2109, "value": "思想" },
  { "id": 2110, "value": "寛容" },
  { "id": 2111, "value": "全体主義" },
  { "id": 2112, "value": "貿易" },
  { "id": 2113, "value": "悲劇" },
  { "id": 2114, "value": "変革" },
  { "id": 2115, "value": "移行" },
  { "id": 2116, "value": "輸送" },
  { "id": 2117, "value": "航海" },
  { "id": 2118, "value": "交渉" },
  { "id": 2119, "value": "条約" },
  { "id": 2120, "value": "休戦" },
  { "id": 2121, "value": "信頼" },
  { "id": 2122, "value": "真実" },
  { "id": 2123, "value": "誠実さ" },
  { "id": 2124, "value": "専制" },
  { "id": 2125, "value": "理解する" },
  { "id": 2126, "value": "連合" },
  { "id": 2127, "value": "団結" },
  { "id": 2128, "value": "都会" },
  { "id": 2129, "value": "ユートピア" },
  { "id": 2130, "value": "谷" },
  { "id": 2131, "value": "勝利" },
  { "id": 2132, "value": "暴力" },
  { "id": 2133, "value": "美徳" },
  { "id": 2134, "value": "ビジョン" },
  { "id": 2135, "value": "ボランティア活動" },
  { "id": 2136, "value": "航海" },
  { "id": 2137, "value": "戦争" },
  { "id": 2138, "value": "知恵" },
  { "id": 2139, "value": "驚き" },
  { "id": 2140, "value": "崇拝" },
  { "id": 2141, "value": "哀愁" },
  { "id": 2142, "value": "ヨガ" },
  { "id": 2143, "value": "熱狂" },
  { "id": 2144, "value": "禅" }
]
