[
  { "id": 3977, "value": "ああ" },
  { "id": 3980, "value": "えっと" },
  { "id": 3981, "value": "おーい" },
  { "id": 3982, "value": "あー" },
  { "id": 3983, "value": "うわ" },
  { "id": 3984, "value": "ばか" },
  { "id": 3985, "value": "ビンゴ" },
  { "id": 3986, "value": "やばい" },
  { "id": 3987, "value": "ぶー" },
  { "id": 3988, "value": "ブラボー" },
  { "id": 3989, "value": "乾杯" },
  { "id": 3990, "value": "おめでと" },
  { "id": 3991, "value": "しまった" },
  { "id": 3992, "value": "ちぇっ" },
  { "id": 3993, "value": "だよね" },
  { "id": 3994, "value": "ぎゃー" },
  { "id": 3995, "value": "えっ" },
  { "id": 3996, "value": "ひらめき" },
  { "id": 3997, "value": "あらら" },
  { "id": 3998, "value": "おお" },
  { "id": 3999, "value": "わお" },
  { "id": 4001, "value": "はっ" },
  { "id": 4002, "value": "はは" },
  { "id": 4003, "value": "うーん" },
  { "id": 4004, "value": "やった" },
  { "id": 4005, "value": "えっ？" },
  { "id": 4006, "value": "やれやれ" },
  { "id": 4007, "value": "しまった" },
  { "id": 4008, "value": "まあ" },
  { "id": 4009, "value": "なんてこった" },
  { "id": 4010, "value": "いや" },
  { "id": 4011, "value": "ううん" },
  { "id": 4012, "value": "おお" },
  { "id": 4013, "value": "おっと" },
  { "id": 4014, "value": "いてっ" },
  { "id": 4015, "value": "あ痛っ" },
  { "id": 4016, "value": "ほっ" },
  { "id": 4017, "value": "しーっ" },
  { "id": 4018, "value": "おや" },
  { "id": 4019, "value": "静かに" },
  { "id": 4020, "value": "ちっ" },
  { "id": 4021, "value": "うー" },
  { "id": 4022, "value": "はい" },
  { "id": 4023, "value": "なんてこった" },
  { "id": 4024, "value": "ふぅ" },
  { "id": 4025, "value": "えへ" },
  { "id": 4026, "value": "これだ" },
  { "id": 4027, "value": "やっほー" },
  { "id": 4028, "value": "まあね" },
  { "id": 4029, "value": "おおー" },
  { "id": 4030, "value": "わぁ" },
  { "id": 4031, "value": "ぎょっ" },
  { "id": 4032, "value": "うわっ" },
  { "id": 4033, "value": "やったー" },
  { "id": 4034, "value": "いたた" },
  { "id": 4035, "value": "よし" },
  { "id": 4036, "value": "ハロー" },
  { "id": 4037, "value": "こんにちは" },
  { "id": 4038, "value": "げっ" },
  { "id": 4039, "value": "おっとっと" },
  { "id": 4040, "value": "なんだ" },
  { "id": 4041, "value": "あっ" },
  { "id": 4042, "value": "えーっ" },
  { "id": 4043, "value": "あちゃー" },
  { "id": 4044, "value": "ジャーン" },
  { "id": 4045, "value": "ばんざい" },
  { "id": 4046, "value": "ああ残念" },
  { "id": 4047, "value": "むむっ" },
  { "id": 4048, "value": "くそっ" },
  { "id": 4049, "value": "ねえ" },
  { "id": 4050, "value": "おやまあ" },
  { "id": 4051, "value": "了解です" },
  { "id": 4052, "value": "ハレルヤ" },
  { "id": 4053, "value": "君" },
  { "id": 4054, "value": "しまった" },
  { "id": 4055, "value": "最高" },
  { "id": 4056, "value": "素晴らしい" },
  { "id": 4057, "value": "なんてこった" },
  { "id": 4058, "value": "信じられない" },
  { "id": 4059, "value": "すごい" },
  { "id": 4060, "value": "すごくいい" },
  { "id": 4061, "value": "あらまあ" },
  { "id": 4062, "value": "天国だ" },
  { "id": 4063, "value": "あいたた" },
  { "id": 4064, "value": "なんと" },
  { "id": 4065, "value": "おやおや" },
  { "id": 4066, "value": "驚きだ" }
]
